{
  "asset": "HATESYMBOL",
  "name": "HATESYMBOL",
  "icon": "https://raw.githubusercontent.com/pappyg45/Images/refs/heads/main/HATESYMBOL%2048.png",
  "image_large": "https://raw.githubusercontent.com/pappyg45/Images/refs/heads/main/HATESYMBOL.png",
  "description": ""https://github.com/pappyg45/XCP-Mints/blob/main/HATESYMBOL.json"",
  "pgpsig": "GMONEYPEPE",
  "social": [
    { "type": "X", "data": "https://x.com/GMONEYPEPE" },
    { "type": "Website", "data": "https://www.adl.org/resources/hate-symbol/pepe-frog" },
    { "type": "Wayback Machine", "data": "https://web.archive.org/web/20260426214521/https://www.adl.org/resources/hate-symbol/pepe-frog" },
    { "type": "The PEPE Project", "data": "https://pepeproject.com/"}
  ]
}
